bareun/__init__.py
bareun/custom_dict_pb2.py
bareun/custom_dict_pb2.pyi
bareun/custom_dict_pb2_grpc.py
bareun/custom_dict_pb2_grpc.pyi
bareun/dict_common_pb2.py
bareun/dict_common_pb2.pyi
bareun/lang_common_pb2.py
bareun/lang_common_pb2.pyi
bareun/language_service_pb2.py
bareun/language_service_pb2.pyi
bareun/language_service_pb2_grpc.py
bareun/language_service_pb2_grpc.pyi
bareun/revision_service_pb2.py
bareun/revision_service_pb2.pyi
bareun/revision_service_pb2_grpc.py
bareun/revision_service_pb2_grpc.pyi
bareun_apis-0.15.2.dist-info/LICENSE
bareun_apis-0.15.2.dist-info/METADATA
bareun_apis-0.15.2.dist-info/WHEEL
bareun_apis-0.15.2.dist-info/RECORD
