Metadata-Version: 2.3
Name: bareun-apis
Version: 0.15.2
Summary: bareunai-apis contains the python classes generated from the bareun ai APIs, which includes tagger, and so on.
License: BSD-3-Clause
Keywords: bareun,grpc,protobuf,POS tagger,Korean,GEC,Error Corrector
Author: Gihyun YUN
Author-email: gih2yun@baikal.ai
Requires-Python: >=3.6,<4.0
Classifier: Development Status :: 5 - Production/Stable
Classifier: Intended Audience :: Developers
Classifier: Intended Audience :: Education
Classifier: Intended Audience :: Information Technology
Classifier: Intended Audience :: Science/Research
Classifier: License :: OSI Approved :: BSD License
Classifier: Natural Language :: Korean
Classifier: Operating System :: MacOS
Classifier: Operating System :: Microsoft :: Windows
Classifier: Operating System :: OS Independent
Classifier: Operating System :: POSIX
Classifier: Operating System :: Unix
Classifier: Programming Language :: Python :: 3
Classifier: Programming Language :: Python :: 3.6
Classifier: Programming Language :: Python :: 3.7
Classifier: Programming Language :: Python :: 3.8
Classifier: Programming Language :: Python :: 3.9
Classifier: Programming Language :: Python :: 3.10
Classifier: Programming Language :: Python :: 3.11
Classifier: Programming Language :: Python :: 3.12
Classifier: Programming Language :: Python :: 3.13
Classifier: Topic :: Scientific/Engineering
Classifier: Topic :: Scientific/Engineering :: Artificial Intelligence
Classifier: Topic :: Scientific/Engineering :: Information Analysis
Classifier: Topic :: Software Development
Classifier: Topic :: Software Development :: Libraries
Classifier: Typing :: Typed
Requires-Dist: googleapis-common-protos (>=1.56.0,<2.0.0)
Requires-Dist: grpcio (>=1.53.2,<2.0.0)
Requires-Dist: protobuf (>=3.19.4,<4.0.0)
Project-URL: Homepage, https://bareun.ai/
Project-URL: Repository, https://github.com/bareun-nlp/bareun-apis
